Metadata-Version: 2.1
Name: json-simple-manager
Version: 1.0
Summary: Pequena biblioteca para validação e manipulação de JSONs
Author: Alan Reis Anjos
Author-email: alanreisanjo@gmail.com
License: GPL 3.0
Keywords: JSON Simple Manager
License-File: LICENSE
